pilibr/__init__.py
pilibr/pilibr.py
pilibr-0.0.1.dist-info/licenses/LICENSE
pilibr-0.0.1.dist-info/METADATA
pilibr-0.0.1.dist-info/WHEEL
pilibr-0.0.1.dist-info/top_level.txt
pilibr-0.0.1.dist-info/RECORD
