Metadata-Version: 2.4
Name: pilibr
Version: 0.0.1
Summary: A Python package for Pi calculations.
Author-email: nya~ <noemail@example.com>
License: Apache-2.0
Requires-Python: >=3
License-File: LICENSE
Dynamic: license-file
